jumpstarter_driver_ridesx/__init__.py
jumpstarter_driver_ridesx/client.py
jumpstarter_driver_ridesx/driver.py
jumpstarter_driver_ridesx/driver_test.py
jumpstarter_driver_ridesx/tmp.txt
jumpstarter_driver_ridesx-0.7.4.dist-info/METADATA
jumpstarter_driver_ridesx-0.7.4.dist-info/WHEEL
jumpstarter_driver_ridesx-0.7.4.dist-info/RECORD
